feetech/__init__.py
feetech/client.py
tetra_feetech-0.1.0.dist-info/LICENSE
tetra_feetech-0.1.0.dist-info/METADATA
tetra_feetech-0.1.0.dist-info/WHEEL
tetra_feetech-0.1.0.dist-info/top_level.txt
tetra_feetech-0.1.0.dist-info/RECORD
