Metadata-Version: 2.2
Name: tetra-feetech
Version: 0.1.0
Summary: A more ergonomic wrapper for the feetech Python SDK
Author-email: Brian Smith <brian@tetradynamics.ai>
License: MIT License
Project-URL: Homepage, https://github.com/tetra-dynamics/tetra-feetech
Project-URL: Repository, https://github.com/tetra-dynamics/tetra-feetech
License-File: LICENSE
Requires-Dist: feetech-servo-sdk
